docs
examples
frf
ops
