Metadata-Version: 2.1
Name: frf
Version: 0.10.6
Summary: FastAPI RESt Framework
Home-page: https://gitlab.com/unimatrixone
Author: Cochise Ruhulessin
Author-email: cochise.ruhulessin@unimatrixone.io
License: UNKNOWN
Platform: UNKNOWN
Classifier: Development Status :: 4 - Beta
Classifier: Environment :: Web Environment
Classifier: Framework :: Flask
Classifier: Intended Audience :: Developers
Classifier: Intended Audience :: Financial and Insurance Industry
Classifier: Intended Audience :: Healthcare Industry
Classifier: License :: Other/Proprietary License
Classifier: Operating System :: POSIX
Classifier: Operating System :: POSIX :: Linux
Classifier: Programming Language :: Python :: 3.8
Classifier: Programming Language :: Python :: 3.9
Classifier: Programming Language :: Python :: 3 :: Only
Classifier: Topic :: Internet
Classifier: Topic :: Internet :: WWW/HTTP :: Session
Classifier: Topic :: Software Development :: Libraries
Provides-Extra: all
Provides-Extra: uvicorn
